{
  "export_time": "2026-01-30T14:53:35.394733",
  "run_metadata": {
    "id": "845a4896-efd1-429d-ac76-f0b2cbf1c1ab",
    "started_at": "2026-01-30 14:48:14.689690+01:00",
    "finished_at": null,
    "status": "running",
    "mode": "prod",
    "listings_found": 0,
    "deals_created": 0,
    "bundles_created": 0,
    "profitable_deals": 0,
    "ai_cost_usd": "0.0000",
    "websearch_calls": 0,
    "duration_sec": null,
    "error_message": null
  },
  "deal_statistics": {
    "total_deals": 28,
    "profitable_deals": 9,
    "very_profitable_deals": 7,
    "avg_profit": "-16.45",
    "max_profit": "150.30",
    "min_profit": "-381.10"
  },
  "bundle_statistics": {
    "total_bundles": 2,
    "profitable_bundles": 0,
    "avg_bundle_profit": "-265.05"
  },
  "strategy_breakdown": {
    "skip": 19,
    "watch": 7,
    "buy_now": 2
  }
}